Workbook

Sheet Assumptions
A1: GLOBAL ASSUMPTIONS
A2: WACC | B2: 0.135
A3: Terminal growth g | B3: 0.04
A4: Tax rate | B4: 0.15
A5: Shares outstanding (m) | B5: 435
A6: USD/HKD | B6: 7.8
A7: Net cash (US$m) | B7: 550 | C7: net IPO proceeds plus pre-IPO cash; preferred shares convert at IPO
A8: Market price (HK$) | B8: 2046
A9: 2025 revenue (US$m) | B9: 102
A10: 2026E revenue (US$m) | B10: 200

Sheet Bear
A1: DCF - Bear scenario
A2: growth start (2027) | B2: 0.4
A3: growth end (2035) | B3: 0.06
A4: start op margin | B4: -0.3
A5: terminal op margin | B5: 0.18
A6: sales-to-capital | B6: 2
A8: Year | B8: i | C8: growth | D8: revenue | E8: op margin | F8: EBIT | G8: cash tax | H8: NOL end | I8: NOPAT | J8: dRev | K8: reinvest | L8: FCFF | M8: disc | N8: PV
A9: 2026 | B9: 0 | C9: =Assumptions!$B$10/Assumptions!$B$9-1 | D9: =Assumptions!$B$10 | E9: =$B$4+($B$5-$B$4)*B9/9 | F9: =D9*E9 | G9: =IF(F9<0,0,MAX(F9-0,0)*Assumptions!$B$4) | H9: =IF(F9<0,0-F9,MAX(0-F9,0)) | I9: =F9-G9 | J9: =D9-Assumptions!$B$9 | K9: =MAX(J9,0)/$B$6 | L9: =I9-K9 | M9: =1/(1+Assumptions!$B$2)^(B9+1) | N9: =L9*M9
A10: 2027 | B10: 1 | C10: =$B$2+($B$3-$B$2)*(B10-1)/8 | D10: =D9*(1+C10) | E10: =$B$4+($B$5-$B$4)*B10/9 | F10: =D10*E10 | G10: =IF(F10<0,0,MAX(F10-H9,0)*Assumptions!$B$4) | H10: =IF(F10<0,H9-F10,MAX(H9-F10,0)) | I10: =F10-G10 | J10: =D10-D9 | K10: =MAX(J10,0)/$B$6 | L10: =I10-K10 | M10: =1/(1+Assumptions!$B$2)^(B10+1) | N10: =L10*M10
A11: 2028 | B11: 2 | C11: =$B$2+($B$3-$B$2)*(B11-1)/8 | D11: =D10*(1+C11) | E11: =$B$4+($B$5-$B$4)*B11/9 | F11: =D11*E11 | G11: =IF(F11<0,0,MAX(F11-H10,0)*Assumptions!$B$4) | H11: =IF(F11<0,H10-F11,MAX(H10-F11,0)) | I11: =F11-G11 | J11: =D11-D10 | K11: =MAX(J11,0)/$B$6 | L11: =I11-K11 | M11: =1/(1+Assumptions!$B$2)^(B11+1) | N11: =L11*M11
A12: 2029 | B12: 3 | C12: =$B$2+($B$3-$B$2)*(B12-1)/8 | D12: =D11*(1+C12) | E12: =$B$4+($B$5-$B$4)*B12/9 | F12: =D12*E12 | G12: =IF(F12<0,0,MAX(F12-H11,0)*Assumptions!$B$4) | H12: =IF(F12<0,H11-F12,MAX(H11-F12,0)) | I12: =F12-G12 | J12: =D12-D11 | K12: =MAX(J12,0)/$B$6 | L12: =I12-K12 | M12: =1/(1+Assumptions!$B$2)^(B12+1) | N12: =L12*M12
A13: 2030 | B13: 4 | C13: =$B$2+($B$3-$B$2)*(B13-1)/8 | D13: =D12*(1+C13) | E13: =$B$4+($B$5-$B$4)*B13/9 | F13: =D13*E13 | G13: =IF(F13<0,0,MAX(F13-H12,0)*Assumptions!$B$4) | H13: =IF(F13<0,H12-F13,MAX(H12-F13,0)) | I13: =F13-G13 | J13: =D13-D12 | K13: =MAX(J13,0)/$B$6 | L13: =I13-K13 | M13: =1/(1+Assumptions!$B$2)^(B13+1) | N13: =L13*M13
A14: 2031 | B14: 5 | C14: =$B$2+($B$3-$B$2)*(B14-1)/8 | D14: =D13*(1+C14) | E14: =$B$4+($B$5-$B$4)*B14/9 | F14: =D14*E14 | G14: =IF(F14<0,0,MAX(F14-H13,0)*Assumptions!$B$4) | H14: =IF(F14<0,H13-F14,MAX(H13-F14,0)) | I14: =F14-G14 | J14: =D14-D13 | K14: =MAX(J14,0)/$B$6 | L14: =I14-K14 | M14: =1/(1+Assumptions!$B$2)^(B14+1) | N14: =L14*M14
A15: 2032 | B15: 6 | C15: =$B$2+($B$3-$B$2)*(B15-1)/8 | D15: =D14*(1+C15) | E15: =$B$4+($B$5-$B$4)*B15/9 | F15: =D15*E15 | G15: =IF(F15<0,0,MAX(F15-H14,0)*Assumptions!$B$4) | H15: =IF(F15<0,H14-F15,MAX(H14-F15,0)) | I15: =F15-G15 | J15: =D15-D14 | K15: =MAX(J15,0)/$B$6 | L15: =I15-K15 | M15: =1/(1+Assumptions!$B$2)^(B15+1) | N15: =L15*M15
A16: 2033 | B16: 7 | C16: =$B$2+($B$3-$B$2)*(B16-1)/8 | D16: =D15*(1+C16) | E16: =$B$4+($B$5-$B$4)*B16/9 | F16: =D16*E16 | G16: =IF(F16<0,0,MAX(F16-H15,0)*Assumptions!$B$4) | H16: =IF(F16<0,H15-F16,MAX(H15-F16,0)) | I16: =F16-G16 | J16: =D16-D15 | K16: =MAX(J16,0)/$B$6 | L16: =I16-K16 | M16: =1/(1+Assumptions!$B$2)^(B16+1) | N16: =L16*M16
A17: 2034 | B17: 8 | C17: =$B$2+($B$3-$B$2)*(B17-1)/8 | D17: =D16*(1+C17) | E17: =$B$4+($B$5-$B$4)*B17/9 | F17: =D17*E17 | G17: =IF(F17<0,0,MAX(F17-H16,0)*Assumptions!$B$4) | H17: =IF(F17<0,H16-F17,MAX(H16-F17,0)) | I17: =F17-G17 | J17: =D17-D16 | K17: =MAX(J17,0)/$B$6 | L17: =I17-K17 | M17: =1/(1+Assumptions!$B$2)^(B17+1) | N17: =L17*M17
A18: 2035 | B18: 9 | C18: =$B$2+($B$3-$B$2)*(B18-1)/8 | D18: =D17*(1+C18) | E18: =$B$4+($B$5-$B$4)*B18/9 | F18: =D18*E18 | G18: =IF(F18<0,0,MAX(F18-H17,0)*Assumptions!$B$4) | H18: =IF(F18<0,H17-F18,MAX(H17-F18,0)) | I18: =F18-G18 | J18: =D18-D17 | K18: =MAX(J18,0)/$B$6 | L18: =I18-K18 | M18: =1/(1+Assumptions!$B$2)^(B18+1) | N18: =L18*M18
A20: Sum PV (explicit) | B20: =SUM(N9:N18)
A21: Terminal value | B21: =L18*(1+Assumptions!$B$3)/(Assumptions!$B$2-Assumptions!$B$3)
A22: PV terminal | B22: =B21*M18
A23: Enterprise value | B23: =B20+B22
A24: Equity value (US$m) | B24: =B23+Assumptions!$B$7
A25: Per share (US$) | B25: =B24/Assumptions!$B$5
A26: Per share (HK$) | B26: =B25*Assumptions!$B$6

Sheet Base
A1: DCF - Base scenario
A2: growth start (2027) | B2: 0.56
A3: growth end (2035) | B3: 0.08
A4: start op margin | B4: -0.3
A5: terminal op margin | B5: 0.28
A6: sales-to-capital | B6: 1.8
A8: Year | B8: i | C8: growth | D8: revenue | E8: op margin | F8: EBIT | G8: cash tax | H8: NOL end | I8: NOPAT | J8: dRev | K8: reinvest | L8: FCFF | M8: disc | N8: PV
A9: 2026 | B9: 0 | C9: =Assumptions!$B$10/Assumptions!$B$9-1 | D9: =Assumptions!$B$10 | E9: =$B$4+($B$5-$B$4)*B9/9 | F9: =D9*E9 | G9: =IF(F9<0,0,MAX(F9-0,0)*Assumptions!$B$4) | H9: =IF(F9<0,0-F9,MAX(0-F9,0)) | I9: =F9-G9 | J9: =D9-Assumptions!$B$9 | K9: =MAX(J9,0)/$B$6 | L9: =I9-K9 | M9: =1/(1+Assumptions!$B$2)^(B9+1) | N9: =L9*M9
A10: 2027 | B10: 1 | C10: =$B$2+($B$3-$B$2)*(B10-1)/8 | D10: =D9*(1+C10) | E10: =$B$4+($B$5-$B$4)*B10/9 | F10: =D10*E10 | G10: =IF(F10<0,0,MAX(F10-H9,0)*Assumptions!$B$4) | H10: =IF(F10<0,H9-F10,MAX(H9-F10,0)) | I10: =F10-G10 | J10: =D10-D9 | K10: =MAX(J10,0)/$B$6 | L10: =I10-K10 | M10: =1/(1+Assumptions!$B$2)^(B10+1) | N10: =L10*M10
A11: 2028 | B11: 2 | C11: =$B$2+($B$3-$B$2)*(B11-1)/8 | D11: =D10*(1+C11) | E11: =$B$4+($B$5-$B$4)*B11/9 | F11: =D11*E11 | G11: =IF(F11<0,0,MAX(F11-H10,0)*Assumptions!$B$4) | H11: =IF(F11<0,H10-F11,MAX(H10-F11,0)) | I11: =F11-G11 | J11: =D11-D10 | K11: =MAX(J11,0)/$B$6 | L11: =I11-K11 | M11: =1/(1+Assumptions!$B$2)^(B11+1) | N11: =L11*M11
A12: 2029 | B12: 3 | C12: =$B$2+($B$3-$B$2)*(B12-1)/8 | D12: =D11*(1+C12) | E12: =$B$4+($B$5-$B$4)*B12/9 | F12: =D12*E12 | G12: =IF(F12<0,0,MAX(F12-H11,0)*Assumptions!$B$4) | H12: =IF(F12<0,H11-F12,MAX(H11-F12,0)) | I12: =F12-G12 | J12: =D12-D11 | K12: =MAX(J12,0)/$B$6 | L12: =I12-K12 | M12: =1/(1+Assumptions!$B$2)^(B12+1) | N12: =L12*M12
A13: 2030 | B13: 4 | C13: =$B$2+($B$3-$B$2)*(B13-1)/8 | D13: =D12*(1+C13) | E13: =$B$4+($B$5-$B$4)*B13/9 | F13: =D13*E13 | G13: =IF(F13<0,0,MAX(F13-H12,0)*Assumptions!$B$4) | H13: =IF(F13<0,H12-F13,MAX(H12-F13,0)) | I13: =F13-G13 | J13: =D13-D12 | K13: =MAX(J13,0)/$B$6 | L13: =I13-K13 | M13: =1/(1+Assumptions!$B$2)^(B13+1) | N13: =L13*M13
A14: 2031 | B14: 5 | C14: =$B$2+($B$3-$B$2)*(B14-1)/8 | D14: =D13*(1+C14) | E14: =$B$4+($B$5-$B$4)*B14/9 | F14: =D14*E14 | G14: =IF(F14<0,0,MAX(F14-H13,0)*Assumptions!$B$4) | H14: =IF(F14<0,H13-F14,MAX(H13-F14,0)) | I14: =F14-G14 | J14: =D14-D13 | K14: =MAX(J14,0)/$B$6 | L14: =I14-K14 | M14: =1/(1+Assumptions!$B$2)^(B14+1) | N14: =L14*M14
A15: 2032 | B15: 6 | C15: =$B$2+($B$3-$B$2)*(B15-1)/8 | D15: =D14*(1+C15) | E15: =$B$4+($B$5-$B$4)*B15/9 | F15: =D15*E15 | G15: =IF(F15<0,0,MAX(F15-H14,0)*Assumptions!$B$4) | H15: =IF(F15<0,H14-F15,MAX(H14-F15,0)) | I15: =F15-G15 | J15: =D15-D14 | K15: =MAX(J15,0)/$B$6 | L15: =I15-K15 | M15: =1/(1+Assumptions!$B$2)^(B15+1) | N15: =L15*M15
A16: 2033 | B16: 7 | C16: =$B$2+($B$3-$B$2)*(B16-1)/8 | D16: =D15*(1+C16) | E16: =$B$4+($B$5-$B$4)*B16/9 | F16: =D16*E16 | G16: =IF(F16<0,0,MAX(F16-H15,0)*Assumptions!$B$4) | H16: =IF(F16<0,H15-F16,MAX(H15-F16,0)) | I16: =F16-G16 | J16: =D16-D15 | K16: =MAX(J16,0)/$B$6 | L16: =I16-K16 | M16: =1/(1+Assumptions!$B$2)^(B16+1) | N16: =L16*M16
A17: 2034 | B17: 8 | C17: =$B$2+($B$3-$B$2)*(B17-1)/8 | D17: =D16*(1+C17) | E17: =$B$4+($B$5-$B$4)*B17/9 | F17: =D17*E17 | G17: =IF(F17<0,0,MAX(F17-H16,0)*Assumptions!$B$4) | H17: =IF(F17<0,H16-F17,MAX(H16-F17,0)) | I17: =F17-G17 | J17: =D17-D16 | K17: =MAX(J17,0)/$B$6 | L17: =I17-K17 | M17: =1/(1+Assumptions!$B$2)^(B17+1) | N17: =L17*M17
A18: 2035 | B18: 9 | C18: =$B$2+($B$3-$B$2)*(B18-1)/8 | D18: =D17*(1+C18) | E18: =$B$4+($B$5-$B$4)*B18/9 | F18: =D18*E18 | G18: =IF(F18<0,0,MAX(F18-H17,0)*Assumptions!$B$4) | H18: =IF(F18<0,H17-F18,MAX(H17-F18,0)) | I18: =F18-G18 | J18: =D18-D17 | K18: =MAX(J18,0)/$B$6 | L18: =I18-K18 | M18: =1/(1+Assumptions!$B$2)^(B18+1) | N18: =L18*M18
A20: Sum PV (explicit) | B20: =SUM(N9:N18)
A21: Terminal value | B21: =L18*(1+Assumptions!$B$3)/(Assumptions!$B$2-Assumptions!$B$3)
A22: PV terminal | B22: =B21*M18
A23: Enterprise value | B23: =B20+B22
A24: Equity value (US$m) | B24: =B23+Assumptions!$B$7
A25: Per share (US$) | B25: =B24/Assumptions!$B$5
A26: Per share (HK$) | B26: =B25*Assumptions!$B$6

Sheet Bull
A1: DCF - Bull scenario
A2: growth start (2027) | B2: 0.85
A3: growth end (2035) | B3: 0.12
A4: start op margin | B4: -0.3
A5: terminal op margin | B5: 0.35
A6: sales-to-capital | B6: 1.6
A8: Year | B8: i | C8: growth | D8: revenue | E8: op margin | F8: EBIT | G8: cash tax | H8: NOL end | I8: NOPAT | J8: dRev | K8: reinvest | L8: FCFF | M8: disc | N8: PV
A9: 2026 | B9: 0 | C9: =Assumptions!$B$10/Assumptions!$B$9-1 | D9: =Assumptions!$B$10 | E9: =$B$4+($B$5-$B$4)*B9/9 | F9: =D9*E9 | G9: =IF(F9<0,0,MAX(F9-0,0)*Assumptions!$B$4) | H9: =IF(F9<0,0-F9,MAX(0-F9,0)) | I9: =F9-G9 | J9: =D9-Assumptions!$B$9 | K9: =MAX(J9,0)/$B$6 | L9: =I9-K9 | M9: =1/(1+Assumptions!$B$2)^(B9+1) | N9: =L9*M9
A10: 2027 | B10: 1 | C10: =$B$2+($B$3-$B$2)*(B10-1)/8 | D10: =D9*(1+C10) | E10: =$B$4+($B$5-$B$4)*B10/9 | F10: =D10*E10 | G10: =IF(F10<0,0,MAX(F10-H9,0)*Assumptions!$B$4) | H10: =IF(F10<0,H9-F10,MAX(H9-F10,0)) | I10: =F10-G10 | J10: =D10-D9 | K10: =MAX(J10,0)/$B$6 | L10: =I10-K10 | M10: =1/(1+Assumptions!$B$2)^(B10+1) | N10: =L10*M10
A11: 2028 | B11: 2 | C11: =$B$2+($B$3-$B$2)*(B11-1)/8 | D11: =D10*(1+C11) | E11: =$B$4+($B$5-$B$4)*B11/9 | F11: =D11*E11 | G11: =IF(F11<0,0,MAX(F11-H10,0)*Assumptions!$B$4) | H11: =IF(F11<0,H10-F11,MAX(H10-F11,0)) | I11: =F11-G11 | J11: =D11-D10 | K11: =MAX(J11,0)/$B$6 | L11: =I11-K11 | M11: =1/(1+Assumptions!$B$2)^(B11+1) | N11: =L11*M11
A12: 2029 | B12: 3 | C12: =$B$2+($B$3-$B$2)*(B12-1)/8 | D12: =D11*(1+C12) | E12: =$B$4+($B$5-$B$4)*B12/9 | F12: =D12*E12 | G12: =IF(F12<0,0,MAX(F12-H11,0)*Assumptions!$B$4) | H12: =IF(F12<0,H11-F12,MAX(H11-F12,0)) | I12: =F12-G12 | J12: =D12-D11 | K12: =MAX(J12,0)/$B$6 | L12: =I12-K12 | M12: =1/(1+Assumptions!$B$2)^(B12+1) | N12: =L12*M12
A13: 2030 | B13: 4 | C13: =$B$2+($B$3-$B$2)*(B13-1)/8 | D13: =D12*(1+C13) | E13: =$B$4+($B$5-$B$4)*B13/9 | F13: =D13*E13 | G13: =IF(F13<0,0,MAX(F13-H12,0)*Assumptions!$B$4) | H13: =IF(F13<0,H12-F13,MAX(H12-F13,0)) | I13: =F13-G13 | J13: =D13-D12 | K13: =MAX(J13,0)/$B$6 | L13: =I13-K13 | M13: =1/(1+Assumptions!$B$2)^(B13+1) | N13: =L13*M13
A14: 2031 | B14: 5 | C14: =$B$2+($B$3-$B$2)*(B14-1)/8 | D14: =D13*(1+C14) | E14: =$B$4+($B$5-$B$4)*B14/9 | F14: =D14*E14 | G14: =IF(F14<0,0,MAX(F14-H13,0)*Assumptions!$B$4) | H14: =IF(F14<0,H13-F14,MAX(H13-F14,0)) | I14: =F14-G14 | J14: =D14-D13 | K14: =MAX(J14,0)/$B$6 | L14: =I14-K14 | M14: =1/(1+Assumptions!$B$2)^(B14+1) | N14: =L14*M14
A15: 2032 | B15: 6 | C15: =$B$2+($B$3-$B$2)*(B15-1)/8 | D15: =D14*(1+C15) | E15: =$B$4+($B$5-$B$4)*B15/9 | F15: =D15*E15 | G15: =IF(F15<0,0,MAX(F15-H14,0)*Assumptions!$B$4) | H15: =IF(F15<0,H14-F15,MAX(H14-F15,0)) | I15: =F15-G15 | J15: =D15-D14 | K15: =MAX(J15,0)/$B$6 | L15: =I15-K15 | M15: =1/(1+Assumptions!$B$2)^(B15+1) | N15: =L15*M15
A16: 2033 | B16: 7 | C16: =$B$2+($B$3-$B$2)*(B16-1)/8 | D16: =D15*(1+C16) | E16: =$B$4+($B$5-$B$4)*B16/9 | F16: =D16*E16 | G16: =IF(F16<0,0,MAX(F16-H15,0)*Assumptions!$B$4) | H16: =IF(F16<0,H15-F16,MAX(H15-F16,0)) | I16: =F16-G16 | J16: =D16-D15 | K16: =MAX(J16,0)/$B$6 | L16: =I16-K16 | M16: =1/(1+Assumptions!$B$2)^(B16+1) | N16: =L16*M16
A17: 2034 | B17: 8 | C17: =$B$2+($B$3-$B$2)*(B17-1)/8 | D17: =D16*(1+C17) | E17: =$B$4+($B$5-$B$4)*B17/9 | F17: =D17*E17 | G17: =IF(F17<0,0,MAX(F17-H16,0)*Assumptions!$B$4) | H17: =IF(F17<0,H16-F17,MAX(H16-F17,0)) | I17: =F17-G17 | J17: =D17-D16 | K17: =MAX(J17,0)/$B$6 | L17: =I17-K17 | M17: =1/(1+Assumptions!$B$2)^(B17+1) | N17: =L17*M17
A18: 2035 | B18: 9 | C18: =$B$2+($B$3-$B$2)*(B18-1)/8 | D18: =D17*(1+C18) | E18: =$B$4+($B$5-$B$4)*B18/9 | F18: =D18*E18 | G18: =IF(F18<0,0,MAX(F18-H17,0)*Assumptions!$B$4) | H18: =IF(F18<0,H17-F18,MAX(H17-F18,0)) | I18: =F18-G18 | J18: =D18-D17 | K18: =MAX(J18,0)/$B$6 | L18: =I18-K18 | M18: =1/(1+Assumptions!$B$2)^(B18+1) | N18: =L18*M18
A20: Sum PV (explicit) | B20: =SUM(N9:N18)
A21: Terminal value | B21: =L18*(1+Assumptions!$B$3)/(Assumptions!$B$2-Assumptions!$B$3)
A22: PV terminal | B22: =B21*M18
A23: Enterprise value | B23: =B20+B22
A24: Equity value (US$m) | B24: =B23+Assumptions!$B$7
A25: Per share (US$) | B25: =B24/Assumptions!$B$5
A26: Per share (HK$) | B26: =B25*Assumptions!$B$6

Sheet Summary
A1: VALUATION SUMMARY
A2: Scenario | B2: Prob | C2: Equity (US$m) | D2: Per share (HK$)
A3: Bear | B3: 0.35 | C3: =Bear!B24 | D3: =Bear!B26
A4: Base | B4: 0.45 | C4: =Base!B24 | D4: =Base!B26
A5: Bull | B5: 0.2 | C5: =Bull!B24 | D5: =Bull!B26
A6: PROB-WEIGHTED | C6: =SUMPRODUCT(B3:B5,C3:C5)/SUM(B3:B5) | D6: =SUMPRODUCT(B3:B5,D3:D5)/SUM(B3:B5)
A7: Market price (HK$) | B7: =Assumptions!B8
A8: DCF value as % of market | B8: =D6/B7
A9: Market equity value / revenue | B9: =(Assumptions!B8*Assumptions!B5/Assumptions!B6)/Assumptions!B10
